{
    "classroom_info": {
        "building": "5号楼",
        "classroom": "0104",
        "floor": "1"
    },
    "courses": [
        {
            "class_name": "材料成形工艺[01]",
            "weeks": [
                1,
                2,
                3,
                4,
                5,
                6,
                7,
                8,
                9,
                10,
                11,
                12,
                13,
                14,
                15,
                16,
                17
            ],
            "day": 1,
            "sections": [
                1,
                2
            ],
            "teacher_name": "李云涛,田银宝"
        },
        {
            "class_name": "应用光谱解析[02]",
            "weeks": [
                1,
                2,
                3,
                4,
                5,
                8,
                9,
                10,
                11,
                12,
                13,
                14,
                15,
                16,
                17
            ],
            "day": 1,
            "sections": [
                3,
                4
            ],
            "teacher_name": "薛松"
        },
        {
            "class_name": "JAVA语言程序设计[01]",
            "weeks": [
                1,
                2,
                3,
                4,
                5,
                6,
                7,
                8,
                9,
                10,
                11,
                12,
                13
            ],
            "day": 2,
            "sections": [
                1,
                2
            ],
            "teacher_name": "李磊"
        },
        {
            "class_name": "电力电子技术[02]",
            "weeks": [
                1,
                2,
                3,
                4,
                5,
                6,
                7,
                8,
                9,
                10,
                11,
                12,
                13,
                14
            ],
            "day": 3,
            "sections": [
                1,
                2
            ],
            "teacher_name": "王云亮,岳有军,李大华"
        },
        {
            "class_name": "计算思维与程序设计基础（C语言）[02]",
            "weeks": [
                3,
                4,
                5,
                6,
                7,
                8,
                9,
                12,
                13,
                14,
                15,
                16,
                17,
                18
            ],
            "day": 4,
            "sections": [
                1,
                2
            ],
            "teacher_name": "彭旭东"
        },
        {
            "class_name": "化工技术基础[01]",
            "weeks": [
                1,
                2,
                3,
                4,
                5,
                8,
                9,
                10,
                11,
                12,
                13,
                14,
                15,
                16
            ],
            "day": 5,
            "sections": [
                1,
                2
            ],
            "teacher_name": "王瑞"
        },
        {
            "class_name": "高等数学AⅠ[09]",
            "weeks": [
                3,
                4,
                5,
                6,
                7,
                8,
                9,
                10,
                11,
                12,
                13,
                14,
                15,
                16,
                17,
                18
            ],
            "day": 2,
            "sections": [
                3,
                4
            ],
            "teacher_name": "宋云燕"
        },
        {
            "class_name": "高等代数Ⅱ[01]",
            "weeks": [
                1,
                2,
                3,
                4,
                5,
                6,
                7,
                8,
                9,
                10,
                11,
                12,
                13,
                14,
                15,
                16,
                17
            ],
            "day": 3,
            "sections": [
                3,
                4
            ],
            "teacher_name": "宋眉眉"
        },
        {
            "class_name": "功能化学品化学[01]",
            "weeks": [
                1,
                2,
                3,
                4,
                5,
                9,
                10,
                11,
                12,
                13,
                14,
                15,
                16,
                17
            ],
            "day": 4,
            "sections": [
                3,
                4
            ],
            "teacher_name": "庞成才"
        },
        {
            "class_name": "高等代数Ⅱ[01]",
            "weeks": [
                1,
                2,
                3,
                4,
                5,
                6,
                7,
                8,
                9,
                10,
                11,
                12,
                13,
                14,
                15,
                16,
                17
            ],
            "day": 5,
            "sections": [
                3,
                4
            ],
            "teacher_name": "宋眉眉"
        },
        {
            "class_name": "功能化学品化学[01]",
            "weeks": [
                2,
                4,
                10,
                12,
                14,
                16
            ],
            "day": 1,
            "sections": [
                5,
                6
            ],
            "teacher_name": "庞成才"
        },
        {
            "class_name": "职业危害与防治[01]",
            "weeks": [
                12,
                13,
                14,
                15,
                16,
                17,
                18
            ],
            "day": 1,
            "sections": [
                7,
                8
            ],
            "teacher_name": "王晓丽"
        },
        {
            "class_name": "安全检测监控技术[01]",
            "weeks": [
                1,
                2,
                3,
                4,
                5,
                6,
                9,
                10,
                11
            ],
            "day": 1,
            "sections": [
                7,
                8
            ],
            "teacher_name": "胡卫萱"
        },
        {
            "class_name": "生物化学[01]",
            "weeks": [
                2,
                4,
                8,
                10,
                12,
                14,
                16,
                18
            ],
            "day": 2,
            "sections": [
                5,
                6
            ],
            "teacher_name": "葛艳辉"
        },
        {
            "class_name": "化工技术基础[01]",
            "weeks": [
                1,
                3,
                5,
                9,
                11,
                13,
                15,
                17
            ],
            "day": 2,
            "sections": [
                5,
                6
            ],
            "teacher_name": "王瑞"
        },
        {
            "class_name": "应用光谱解析[02]",
            "weeks": [
                3,
                4
            ],
            "day": 3,
            "sections": [
                7,
                8
            ],
            "teacher_name": "薛松"
        },
        {
            "class_name": "高等数学AⅠ[09]",
            "weeks": [
                14,
                15,
                16
            ],
            "day": 3,
            "sections": [
                7,
                8
            ],
            "teacher_name": "宋云燕"
        },
        {
            "class_name": "语音识别与合成技术[01]",
            "weeks": [
                8,
                9,
                10
            ],
            "day": 3,
            "sections": [
                7,
                8
            ],
            "teacher_name": "岳有军"
        },
        {
            "class_name": "材料成形工艺[01]",
            "weeks": [
                1,
                3,
                5,
                7,
                11,
                13,
                15,
                17
            ],
            "day": 4,
            "sections": [
                5,
                6
            ],
            "teacher_name": "李云涛,田银宝"
        },
        {
            "class_name": "船舶局域网技术及应用[01]",
            "weeks": [
                2,
                4,
                6,
                8,
                10,
                12,
                14,
                16
            ],
            "day": 4,
            "sections": [
                5,
                6
            ],
            "teacher_name": "王宗涛"
        },
        {
            "class_name": "JAVA语言程序设计[01]",
            "weeks": [
                1,
                2,
                3,
                4,
                5,
                6,
                7,
                8,
                9,
                10,
                11,
                12,
                13
            ],
            "day": 5,
            "sections": [
                5,
                6
            ],
            "teacher_name": "李磊"
        }
    ],
    "events": [
        {
            "event_name": "教室借用",
            "event_reason": "院排考试",
            "person": "研究生院",
            "weeks": [
                20
            ],
            "day": 1,
            "sections": [
                1,
                2,
                3,
                4
            ]
        },
        {
            "event_name": "教室借用",
            "event_reason": "招聘会",
            "person": "王芳",
            "weeks": [
                7
            ],
            "day": 1,
            "sections": [
                3,
                4
            ]
        },
        {
            "event_name": "考试",
            "event_reason": "高等数学BⅠ",
            "person": "",
            "weeks": [
                19
            ],
            "day": 1,
            "sections": [
                1,
                2
            ]
        },
        {
            "event_name": "考试",
            "event_reason": "美学概论",
            "person": "",
            "weeks": [
                19
            ],
            "day": 2,
            "sections": [
                1,
                2
            ]
        },
        {
            "event_name": "考试",
            "event_reason": "大学物理BII",
            "person": "",
            "weeks": [
                19
            ],
            "day": 4,
            "sections": [
                1,
                2
            ]
        },
        {
            "event_name": "考试",
            "event_reason": "古代汉语Ⅰ",
            "person": "",
            "weeks": [
                19
            ],
            "day": 5,
            "sections": [
                1,
                2
            ]
        },
        {
            "event_name": "教室借用",
            "event_reason": "集中授课工程设计导论",
            "person": "陈炜",
            "weeks": [
                6
            ],
            "day": 6,
            "sections": [
                1,
                2,
                3,
                4
            ]
        },
        {
            "event_name": "教室借用",
            "event_reason": "开会",
            "person": "齐霖",
            "weeks": [
                15
            ],
            "day": 6,
            "sections": [
                1,
                2,
                3,
                4,
                5,
                6,
                7,
                8,
                9,
                10,
                11
            ]
        },
        {
            "event_name": "教室借用",
            "event_reason": "学生活动",
            "person": "李梦菲",
            "weeks": [
                3
            ],
            "day": 6,
            "sections": [
                5,
                6
            ]
        },
        {
            "event_name": "教室借用",
            "event_reason": "集中授课",
            "person": "刘津丽",
            "weeks": [
                8
            ],
            "day": 4,
            "sections": [
                3,
                4
            ]
        },
        {
            "event_name": "考试",
            "event_reason": "集成电路工艺原理",
            "person": "",
            "weeks": [
                18
            ],
            "day": 4,
            "sections": [
                3,
                4
            ]
        },
        {
            "event_name": "考试",
            "event_reason": "建模与辨识",
            "person": "",
            "weeks": [
                18
            ],
            "day": 5,
            "sections": [
                3,
                4
            ]
        },
        {
            "event_name": "教室借用",
            "event_reason": "补课",
            "person": "杨玉玲",
            "weeks": [
                3
            ],
            "day": 1,
            "sections": [
                5,
                6
            ]
        },
        {
            "event_name": "教室借用",
            "event_reason": "院排考试",
            "person": "研究生院",
            "weeks": [
                20
            ],
            "day": 1,
            "sections": [
                5,
                6,
                7,
                8
            ]
        },
        {
            "event_name": "教室借用",
            "event_reason": "集中授课-高等代数",
            "person": "熊晓蕾",
            "weeks": [
                16
            ],
            "day": 3,
            "sections": [
                5,
                6
            ]
        },
        {
            "event_name": "教室借用",
            "event_reason": "开会-教师报告",
            "person": "熊晓蕾",
            "weeks": [
                7
            ],
            "day": 3,
            "sections": [
                5,
                6,
                7,
                8
            ]
        },
        {
            "event_name": "教室借用",
            "event_reason": "党课及党课考试",
            "person": "陈尚尚",
            "weeks": [
                12
            ],
            "day": 3,
            "sections": [
                7,
                8
            ]
        },
        {
            "event_name": "教室借用",
            "event_reason": "党课及党课考试",
            "person": "陈尚尚",
            "weeks": [
                12
            ],
            "day": 3,
            "sections": [
                7,
                8
            ]
        },
        {
            "event_name": "考试",
            "event_reason": "新生入学综合测试",
            "person": "",
            "weeks": [
                1
            ],
            "day": 3,
            "sections": [
                5,
                6
            ]
        },
        {
            "event_name": "考试",
            "event_reason": "新生入学综合测试",
            "person": "",
            "weeks": [
                1
            ],
            "day": 3,
            "sections": [
                5,
                6
            ]
        },
        {
            "event_name": "考试",
            "event_reason": "工程电磁场",
            "person": "",
            "weeks": [
                11
            ],
            "day": 3,
            "sections": [
                5,
                6
            ]
        },
        {
            "event_name": "考试",
            "event_reason": "数据挖掘",
            "person": "",
            "weeks": [
                18
            ],
            "day": 3,
            "sections": [
                5,
                6
            ]
        },
        {
            "event_name": "考试",
            "event_reason": "大学英语（初级）",
            "person": "",
            "weeks": [
                19
            ],
            "day": 3,
            "sections": [
                5,
                6
            ]
        },
        {
            "event_name": "教室借用",
            "event_reason": "学生活动，党员积极分子培训",
            "person": "李一洁",
            "weeks": [
                9
            ],
            "day": 4,
            "sections": [
                5,
                6
            ]
        },
        {
            "event_name": "考试",
            "event_reason": "中国近现代史纲要",
            "person": "",
            "weeks": [
                19
            ],
            "day": 4,
            "sections": [
                5,
                6
            ]
        },
        {
            "event_name": "教室借用",
            "event_reason": "补课",
            "person": "王志欣",
            "weeks": [
                15,
                16
            ],
            "day": 5,
            "sections": [
                5,
                6
            ]
        },
        {
            "event_name": "考试",
            "event_reason": "机械CAD/CAM",
            "person": "",
            "weeks": [
                14
            ],
            "day": 5,
            "sections": [
                5,
                6
            ]
        },
        {
            "event_name": "教室借用",
            "event_reason": "补课",
            "person": "杨玉玲",
            "weeks": [
                10
            ],
            "day": 4,
            "sections": [
                7,
                8
            ]
        },
        {
            "event_name": "教室借用",
            "event_reason": "布置考场",
            "person": "郝丽芳",
            "weeks": [
                16
            ],
            "day": 5,
            "sections": [
                7,
                8
            ]
        },
        {
            "event_name": "教室借用",
            "event_reason": "开会",
            "person": "齐霖",
            "weeks": [
                15
            ],
            "day": 5,
            "sections": [
                7,
                8,
                9,
                10,
                11
            ]
        },
        {
            "event_name": "教室借用",
            "event_reason": "团委破冰活动",
            "person": "刘楠",
            "weeks": [
                6
            ],
            "day": 5,
            "sections": [
                8,
                9,
                10,
                11
            ]
        },
        {
            "event_name": "教室借用",
            "event_reason": "布置考场",
            "person": "郝丽芳",
            "weeks": [
                16
            ],
            "day": 5,
            "sections": [
                9,
                10,
                11
            ]
        },
        {
            "event_name": "教室借用",
            "event_reason": "自习室",
            "person": "热米兰",
            "weeks": [
                3,
                4,
                5,
                6,
                7,
                8,
                9,
                10,
                11,
                12,
                13,
                14,
                15,
                16
            ],
            "day": 1,
            "sections": [
                9,
                10,
                11
            ]
        },
        {
            "event_name": "教室借用",
            "event_reason": "自习室",
            "person": "热米兰",
            "weeks": [
                3,
                4,
                5,
                6,
                7,
                8,
                9,
                10,
                11,
                12,
                13,
                14,
                15,
                16
            ],
            "day": 2,
            "sections": [
                9,
                10,
                11
            ]
        },
        {
            "event_name": "教室借用",
            "event_reason": "自习室",
            "person": "热米兰",
            "weeks": [
                3,
                4,
                5,
                6,
                7,
                8,
                9,
                10,
                11,
                12,
                13,
                14,
                15,
                16
            ],
            "day": 3,
            "sections": [
                9,
                10,
                11
            ]
        },
        {
            "event_name": "教室借用",
            "event_reason": "自习室",
            "person": "热米兰",
            "weeks": [
                3,
                4,
                5,
                6,
                7,
                8,
                9,
                10,
                11,
                12,
                13,
                14,
                15,
                16
            ],
            "day": 4,
            "sections": [
                9,
                10,
                11
            ]
        }
    ]
}